.bumpversion.cfg
.coveragerc
.travis.yml
AUTHORS.rst
CHANGELOG.rst
CONTRIBUTING.rst
HISTORY.rst
LICENSE
MANIFEST.in
Makefile
README.rst
setup.cfg
setup.py
tox.ini
version.py
version_number.py
ci/bootstrap.py
ci/templates/.travis.yml
ci/templates/tox.ini
docs/Makefile
docs/authors.rst
docs/changelog.rst
docs/conf.py
docs/contributing.rst
docs/index.rst
docs/installation.rst
docs/readme.rst
docs/requirements.txt
docs/spelling_wordlist.txt
docs/usage.rst
docs/reference/index.rst
docs/reference/modules.rst
docs/reference/smap.rst
docs/templates/readme.template
docs/templates/usage.template
src/smap/__init__.py
src/smap/_version.py
src/smap/main.py
src/smap/symver.py
src/symver_smap.egg-info/PKG-INFO
src/symver_smap.egg-info/SOURCES.txt
src/symver_smap.egg-info/dependency_links.txt
src/symver_smap.egg-info/entry_points.txt
src/symver_smap.egg-info/not-zip-safe
src/symver_smap.egg-info/top_level.txt
tests/Makefile
tests/conftest.py
tests/test_as_lib.py
tests/test_bump_version.py
tests/test_check.py
tests/test_check_files.py
tests/test_clean_symbols.py
tests/test_get_info_from_release_string.py
tests/test_get_version_from_string.py
tests/test_new.py
tests/test_overwrite_protected.py
tests/test_script.py
tests/test_update.py
tests/data_template/test_as_lib/base.map
tests/data_template/test_as_lib/empty_map.stdout
tests/data_template/test_as_lib/new_default_name.stdout
tests/data_template/test_as_lib/new_different_name.stdout
tests/data_template/test_as_lib/print_released.stdout
tests/data_template/test_as_lib/released.map
tests/data_template/test_as_lib/symbol.in
tests/data_template/test_as_lib/update_default_name.stdout
tests/data_template/test_as_lib/update_different_name.stdout
tests/data_template/test_as_lib/without_prefix.map
tests/data_template/test_as_lib/without_similar_prefix.map
tests/data_template/test_as_lib/without_version.map
tests/data_template/test_bump_version/tc1.yaml
tests/data_template/test_check/base.map
tests/data_template/test_check/baseless.map
tests/data_template/test_check/broken_maps.yaml
tests/data_template/test_check/circular_dependency.map
tests/data_template/test_check/double_previous.map
tests/data_template/test_check/double_release.map
