Metadata-Version: 1.1
Name: symver-smap
Version: 0.2.5
Summary: A helper for library maintainers to use symbol versioning 
Home-page: https://github.com/ansasaki/smap
Author: Anderson Toshiyuki Sasaki
Author-email: ansasaki@redhat.com
License: MIT license
Keywords: symver smap symbol version versioning linker script library maintenance
Platform: UNKNOWN
Classifier: Development Status :: 2 - Pre-Alpha
Classifier: Intended Audience :: Developers
Classifier: Topic :: Software Development :: Build Tools
Classifier: License :: OSI Approved :: MIT License
Classifier: Natural Language :: English
Classifier: Programming Language :: Python :: 2
Classifier: Programming Language :: Python :: 2.7
Classifier: Programming Language :: Python :: 3
Classifier: Programming Language :: Python :: 3.4
Classifier: Programming Language :: Python :: 3.5
Classifier: Programming Language :: Python :: 3.6
